{
  "updated_at": "2025-11-03T20:46:28.904Z",
  "source": "funpay",
  "pairs": {
    "le:gold": {
      "game": "le",
      "currency": "gold",
      "price_RUB": 0,
      "change_24h": null,
      "change_7d": null,
      "updated_at": "2025-11-03T20:46:27.537Z",
      "trades_tops": [],
      "error": "page.locator(...).first(...).catch is not a function"
    },
    "tli:flame-elementium": {
      "game": "tli",
      "currency": "flame-elementium",
      "price_RUB": 0,
      "change_24h": null,
      "change_7d": null,
      "updated_at": "2025-11-03T20:46:27.876Z",
      "trades_tops": [],
      "error": "page.locator(...).first(...).catch is not a function"
    },
    "poe1:divine-orb": {
      "game": "poe1",
      "currency": "divine-orb",
      "price_RUB": 0,
      "change_24h": null,
      "change_7d": null,
      "updated_at": "2025-11-03T20:46:28.312Z",
      "trades_tops": [],
      "error": "page.locator(...).first(...).catch is not a function"
    },
    "poe2:divine-orb": {
      "game": "poe2",
      "currency": "divine-orb",
      "price_RUB": 0,
      "change_24h": null,
      "change_7d": null,
      "updated_at": "2025-11-03T20:46:28.859Z",
      "trades_tops": [],
      "error": "page.locator(...).first(...).catch is not a function"
    }
  }
}