{
  "updated_at": "2025-09-19T09:55:02.778Z",
  "source": "funpay",
  "pairs": {
    "le:gold": {
      "game": "le",
      "currency": "gold",
      "price_RUB": 1.84,
      "change_24h": null,
      "change_7d": null,
      "updated_at": "2025-09-19T09:55:05.609Z",
      "trades_tops": [
        1.84,
        1.88,
        2.28,
        2.37,
        3.45
      ],
      "error": null
    },
    "tli:flame-elementium": {
      "game": "tli",
      "currency": "flame-elementium",
      "price_RUB": 0,
      "change_24h": null,
      "change_7d": null,
      "updated_at": null,
      "trades_tops": [],
      "error": "waitAny timeout 20000ms. selectors: .tc-item .tc-price, table.tc-table .tc-item .tc-price, .showcase-table .tc-item .tc-price"
    },
    "poe1:divine-orb": {
      "game": "poe1",
      "currency": "divine-orb",
      "price_RUB": 0.91,
      "change_24h": null,
      "change_7d": null,
      "updated_at": "2025-09-19T09:55:30.275Z",
      "trades_tops": [
        0.91,
        0.92,
        0.95,
        0.97,
        1.03
      ],
      "error": null
    },
    "poe2:divine-orb": {
      "game": "poe2",
      "currency": "divine-orb",
      "price_RUB": 0.0182,
      "change_24h": null,
      "change_7d": null,
      "updated_at": "2025-09-19T09:56:04.562Z",
      "trades_tops": [
        0.0182,
        0.03,
        0.034,
        0.035,
        0.036
      ],
      "error": null
    }
  }
}